odoo/addons/account_fiscal_l10n_visibility/__init__.py
odoo/addons/account_fiscal_l10n_visibility/__manifest__.py
odoo/addons/account_fiscal_l10n_visibility/views/account_settings_views.xml
odoo14_addon_account_fiscal_l10n_visibility-14.0.1.0.2.dist-info/METADATA
odoo14_addon_account_fiscal_l10n_visibility-14.0.1.0.2.dist-info/WHEEL
odoo14_addon_account_fiscal_l10n_visibility-14.0.1.0.2.dist-info/top_level.txt
odoo14_addon_account_fiscal_l10n_visibility-14.0.1.0.2.dist-info/RECORD
