Metadata-Version: 2.1
Name: odoo14-addon-account-fiscal-l10n-visibility
Version: 14.0.1.0.2
Summary: Enhances fiscal localization settings in Odoo by customizing visibility and editability based on existing accounting entries.
Home-page: https://git.coopdevs.org/coopdevs/odoo/odoo-addons/odoo14-addons
Author: Coopdevs
License: UNKNOWN
Platform: UNKNOWN
Classifier: Programming Language :: Python
Classifier: Framework :: Odoo
Classifier: Framework :: Odoo :: 14.0
Requires-Python: >=3.6
Requires-Dist: odoo <14.1dev,>=14.0a
